denarolib/__init__.py
denarolib/denarolib.py
denarolib-1.0.2.dist-info/licenses/LICENSE
denarolib-1.0.2.dist-info/METADATA
denarolib-1.0.2.dist-info/WHEEL
denarolib-1.0.2.dist-info/top_level.txt
denarolib-1.0.2.dist-info/RECORD
