Metadata-Version: 2.4
Name: denarolib
Version: 1.0.2
Summary: A Python library for interacting with the Denaro cyptocurrency
Author-email: Gamer000gaming <gamer07340@gmail.com>
License-Expression: MIT
Classifier: Programming Language :: Python :: 3
Classifier: Operating System :: OS Independent
Requires-Python: >=3.9
License-File: LICENSE
Dynamic: license-file
